sl_up/__init__.py
sl_up/log_parser.py
sl_up/main.py
sl_up/operations.py
sl_up/terminal.py
sl_up-0.1.1.dist-info/LICENSE
sl_up-0.1.1.dist-info/METADATA
sl_up-0.1.1.dist-info/WHEEL
sl_up-0.1.1.dist-info/entry_points.txt
sl_up-0.1.1.dist-info/RECORD
