Metadata-Version: 2.1
Name: sl-up
Version: 0.1.1
Summary: Interactive Sapling SCM smartlog cli tool
License: GPL-3.0-or-later
Author: Roy Rothenberg
Author-email: royrothenberg@gmail.com
Requires-Python: >=3.10,<4.0
Classifier: License :: OSI Approved :: GNU General Public License v3 or later (GPLv3+)
Classifier: Programming Language :: Python :: 3
Classifier: Programming Language :: Python :: 3.10
Classifier: Programming Language :: Python :: 3.11
Classifier: Programming Language :: Python :: 3.12
